multipie/__init__.py
multipie/const.py
multipie/binary_data/BaseAtomicMultipoleDataset.pkl
multipie/binary_data/CharacterPGSet.pkl
multipie/binary_data/ClebschGordanPGSet.pkl
multipie/binary_data/HarmonicsPGSet.pkl
multipie/binary_data/ResponseTensorPGSet.pkl
multipie/binary_data/SymmetryOperationGSet.pkl
multipie/binary_data/VirtualClusterPGSet.pkl
multipie/binary_data/WyckoffGSet.pkl
multipie/character/character_pg.py
multipie/character/character_pg_set.py
multipie/clebsch_gordan/clebsch_gordan_pg.py
multipie/clebsch_gordan/clebsch_gordan_pg_set.py
multipie/data/data_atomic_multipoles.py
multipie/data/data_cartesian_to_ch_harmoncis.py
multipie/data/data_character_table.py
multipie/data/data_compatibility_relation.py
multipie/data/data_harmonics.py
multipie/data/data_harmonics_real.py
multipie/data/data_no_space_group.py
multipie/data/data_product_decomp.py
multipie/data/data_symmetry_operation_pg.py
multipie/data/data_symmetry_operation_sg.py
multipie/data/data_tag_harmonics_alias.py
multipie/data/data_tag_irrep.py
multipie/data/data_tag_point_group.py
multipie/data/data_tag_space_group.py
multipie/data/data_transform_matrix.py
multipie/data/data_virtual_cluster_real.py
multipie/data/data_wyckoff_pg.py
multipie/data/data_wyckoff_sg.py
multipie/group/point_group.py
multipie/group/space_group.py
multipie/harmonics/harmonics.py
multipie/harmonics/harmonics_complex_pg.py
multipie/harmonics/harmonics_complex_pg_set.py
multipie/harmonics/harmonics_pg.py
multipie/harmonics/harmonics_pg_set.py
multipie/harmonics/util/equivalent_operator.py
multipie/model/construct_model.py
multipie/model/create_model.py
multipie/model/material_model.py
multipie/model/multipie_manager.py
multipie/model/symmetry_adapted_model.py
multipie/model/util/atomic_matrix_util.py
multipie/model/util/create_pdf.py
multipie/model/util/symmetry_adapted_model_util.py
multipie/multipole/base/base_atomic_multipole_dataset.py
multipie/multipole/base/base_atomic_multipole_set.py
multipie-1.3.3.dist-info/licenses/LICENSE
multipie-1.3.3.dist-info/METADATA
multipie-1.3.3.dist-info/WHEEL
multipie-1.3.3.dist-info/entry_points.txt
multipie-1.3.3.dist-info/top_level.txt
multipie-1.3.3.dist-info/RECORD
