Metadata-Version: 2.4
Name: multipie
Version: 1.3.3
Summary: A python library for crystallographic symmetry operations and Symmetry-Adapted Multipole Basis (SAMB).
Author-email: Hiroaki Kusunose <hiroaki.kusunose@gmail.com>, Rikuto Oiwa <ro.qp.07@gmail.com>
License: MIT
Project-URL: Homepage, https://github.com/CMT-MU/MultiPie
Project-URL: Issues, https://github.com/CMT-MU/MultiPie/issues
Keywords: group theory,condensed matter,materials science,symmetry-adapted basis
Classifier: Intended Audience :: Science/Research
Classifier: Topic :: Scientific/Engineering :: Information Analysis
Classifier: License :: OSI Approved :: MIT License
Classifier: Operating System :: Microsoft :: Windows
Classifier: Operating System :: POSIX
Classifier: Operating System :: MacOS
Classifier: Programming Language :: Python :: 3.9
Classifier: Programming Language :: Python :: 3.10
Classifier: Programming Language :: Python :: 3.11
Classifier: Programming Language :: Python :: 3.12
Requires-Python: >=3.9
License-File: LICENSE
Requires-Dist: black
Requires-Dist: joblib
Requires-Dist: gmpy2
Requires-Dist: click
Requires-Dist: gcoreutils
Provides-Extra: dev
Requires-Dist: jupyter-book; extra == "dev"
Requires-Dist: ghp-import; extra == "dev"
Requires-Dist: jupytext; extra == "dev"
Requires-Dist: qtdraw; extra == "dev"
Dynamic: license-file
